Metadata-Version: 2.1
Name: opyngptchat
Version: 0.4.0
Summary: Supercharge your projects with LLMs. No API keys required.
Author: Pranil Chitre
License-File: LICENSE
Requires-Dist: requests
